compas_triangle/__init__.py
compas_triangle/delaunay.py
compas_triangle/rhino.py
compas_triangle-1.2.1.dist-info/AUTHORS.md
compas_triangle-1.2.1.dist-info/LICENSE.Triangle
compas_triangle-1.2.1.dist-info/METADATA
compas_triangle-1.2.1.dist-info/WHEEL
compas_triangle-1.2.1.dist-info/top_level.txt
compas_triangle-1.2.1.dist-info/RECORD
