Metadata-Version: 2.2
Name: compas_triangle
Version: 1.2.1
Summary: COMPAS-firendly wrappers for the Triangle library
Author-email: tom van mele <tom.v.mele@gmail.com>
Project-URL: Homepage, https://compas-dev.github.io/compas_triangle
Project-URL: Documentation, https://compas-dev.github.io/compas_triangle
Project-URL: Repository, https://github.com/compas-dev/compas_triangle
Project-URL: Changelog, https://github.com/compas-dev/compas_triangle/blob/main/CHANGELOG.md
Project-URL: Issues, https://github.com/compas-dev/compas_triangle/issues
Project-URL: Forum, https://forum.compas-framework.org/
Classifier: Development Status :: 4 - Beta
Classifier: Topic :: Scientific/Engineering
Classifier: Operating System :: Unix
Classifier: Operating System :: POSIX
Classifier: Operating System :: Microsoft :: Windows
Classifier: Programming Language :: Python
Classifier: Programming Language :: Python :: 3
Classifier: Programming Language :: Python :: 3.10
Classifier: Programming Language :: Python :: 3.11
Classifier: Programming Language :: Python :: 3.12
Requires-Python: >=3.9
License-File: LICENSE.Triangle
License-File: AUTHORS.md
Requires-Dist: triangle
Requires-Dist: compas>=2.4
Provides-Extra: dev
Requires-Dist: attrs>=17.4; extra == "dev"
Requires-Dist: black>=22.12.0; extra == "dev"
Requires-Dist: bump-my-version; extra == "dev"
Requires-Dist: compas_invocations2; extra == "dev"
Requires-Dist: compas_notebook; extra == "dev"
Requires-Dist: compas_viewer; extra == "dev"
Requires-Dist: invoke>=0.14; extra == "dev"
Requires-Dist: ruff; extra == "dev"
Requires-Dist: sphinx_compas2_theme; extra == "dev"
Requires-Dist: twine; extra == "dev"
Requires-Dist: wheel; extra == "dev"
